javascript/.__init__.py.swp
javascript/.__init__.py.un~
javascript/__init__.py
javascript-2015.32.57.1.dist-info/METADATA
javascript-2015.32.57.1.dist-info/WHEEL
javascript-2015.32.57.1.dist-info/RECORD
